[{"times":1,"passCost":"2000006#10","cost":"2000008#1"},{"times":2,"passCost":"2000006#20","cost":"2000008#1"},{"times":3,"passCost":"2000006#30","cost":"2000008#1"},{"times":4,"passCost":"2000006#40","cost":"2000008#1"},{"times":5,"passCost":"2000006#50","cost":"2000008#1"},{"times":6,"passCost":"2000006#60","cost":"2000008#1"},{"times":7,"passCost":"2000006#70","cost":"2000008#1"},{"times":8,"passCost":"2000006#80","cost":"2000008#1"},{"times":9,"passCost":"2000006#90","cost":"2000008#1"},{"times":10,"passCost":"2000006#100","cost":"2000008#1"}]