{"resource_point": [{"id": "4000009", "name": "resource_point", "gid": "321", "x": "5421.2", "y": "4782.8", "width": "157", "height": "178", "fog_area": "58", "max_num": "1"}, {"id": "4000014", "name": "resource_point", "gid": "348", "x": "3720", "y": "5160", "width": "98", "height": "75", "fog_area": "49", "max_num": "1"}, {"id": "4000008", "name": "resource_point", "gid": "330", "x": "3878.13", "y": "4900.53", "width": "122", "height": "142", "fog_area": "49", "max_num": "1"}, {"id": "4000008", "name": "resource_point", "gid": "330", "x": "4851.8", "y": "4156.38", "width": "122", "height": "142", "fog_area": "57", "max_num": "1"}, {"id": "4000010", "name": "resource_point", "gid": "329", "x": "4176.89", "y": "3990.01", "width": "141", "height": "199", "fog_area": "57", "max_num": "1"}, {"id": "4000009", "name": "resource_point", "gid": "321", "x": "4031.78", "y": "2753.4", "width": "157", "height": "178", "fog_area": "57", "max_num": "1"}, {"id": "4000011", "name": "resource_point", "gid": "340", "x": "5163.12", "y": "4417.6", "width": "72", "height": "65", "fog_area": "57", "max_num": "1"}, {"id": "4000011", "name": "resource_point", "gid": "340", "x": "5032.95", "y": "4505.58", "width": "72", "height": "65", "fog_area": "57", "max_num": "1"}, {"id": "4000012", "name": "resource_point", "gid": "341", "x": "5083.08", "y": "4256.32", "width": "83", "height": "76", "fog_area": "57", "max_num": "1"}, {"id": "4000012", "name": "resource_point", "gid": "341", "x": "3346.11", "y": "4364.73", "width": "83", "height": "76", "fog_area": "51", "max_num": "1"}, {"id": "4000011", "name": "resource_point", "gid": "340", "x": "3450.27", "y": "5360.19", "width": "72", "height": "65", "fog_area": "49", "max_num": "1"}, {"id": "4000011", "name": "resource_point", "gid": "340", "x": "3303.54", "y": "4476.16", "width": "72", "height": "65", "fog_area": "51", "max_num": "1"}, {"id": "4000008", "name": "resource_point", "gid": "330", "x": "3675.35", "y": "4426.95", "width": "122", "height": "142", "fog_area": "51", "max_num": "1"}, {"id": "4000008", "name": "resource_point", "gid": "330", "x": "3044.46", "y": "4317.78", "width": "122", "height": "142", "fog_area": "51", "max_num": "1"}, {"id": "4000009", "name": "resource_point", "gid": "321", "x": "2474.57", "y": "4285.23", "width": "157", "height": "178", "fog_area": "51", "max_num": "1"}, {"id": "4000009", "name": "resource_point", "gid": "321", "x": "3561.81", "y": "4099.14", "width": "157", "height": "178", "fog_area": "51", "max_num": "1"}, {"id": "4000010", "name": "resource_point", "gid": "329", "x": "3692.61", "y": "4856.1", "width": "141", "height": "199", "fog_area": "51", "max_num": "1"}, {"id": "4000014", "name": "resource_point", "gid": "348", "x": "2610.11", "y": "3430.84", "width": "98", "height": "75", "fog_area": "51", "max_num": "1"}, {"id": "4000011", "name": "resource_point", "gid": "340", "x": "2579.05", "y": "3157.92", "width": "72", "height": "65", "fog_area": "54", "max_num": "1"}, {"id": "4000012", "name": "resource_point", "gid": "341", "x": "2607.57", "y": "3021.83", "width": "83", "height": "76", "fog_area": "54", "max_num": "1"}, {"id": "4000011", "name": "resource_point", "gid": "340", "x": "2709.6", "y": "3245.01", "width": "72", "height": "65", "fog_area": "54", "max_num": "1"}, {"id": "4000011", "name": "resource_point", "gid": "340", "x": "4297.03", "y": "3955.04", "width": "72", "height": "65", "fog_area": "57", "max_num": "1"}, {"id": "4000011", "name": "resource_point", "gid": "340", "x": "3669.06", "y": "3338.29", "width": "72", "height": "65", "fog_area": "54", "max_num": "1"}, {"id": "4000012", "name": "resource_point", "gid": "341", "x": "4182.61", "y": "4103.99", "width": "83", "height": "76", "fog_area": "57", "max_num": "1"}, {"id": "4000008", "name": "resource_point", "gid": "330", "x": "2238.39", "y": "2878.89", "width": "122", "height": "142", "fog_area": "54", "max_num": "1"}, {"id": "4000009", "name": "resource_point", "gid": "321", "x": "2211.38", "y": "2679.62", "width": "157", "height": "178", "fog_area": "54", "max_num": "1"}, {"id": "4000010", "name": "resource_point", "gid": "329", "x": "2391.34", "y": "2556.41", "width": "141", "height": "199", "fog_area": "54", "max_num": "1"}, {"id": "4000010", "name": "resource_point", "gid": "329", "x": "2573.39", "y": "4550.01", "width": "141", "height": "199", "fog_area": "51", "max_num": "1"}, {"id": "4000010", "name": "resource_point", "gid": "329", "x": "2525.16", "y": "2168.11", "width": "141", "height": "199", "fog_area": "54", "max_num": "1"}, {"id": "4000010", "name": "resource_point", "gid": "329", "x": "3366.63", "y": "2268.91", "width": "141", "height": "199", "fog_area": "54", "max_num": "1"}, {"id": "4000009", "name": "resource_point", "gid": "321", "x": "3082.52", "y": "3087.7", "width": "157", "height": "178", "fog_area": "54", "max_num": "1"}, {"id": "4000009", "name": "resource_point", "gid": "321", "x": "2793.89", "y": "3596.43", "width": "157", "height": "178", "fog_area": "51", "max_num": "1"}, {"id": "4000009", "name": "resource_point", "gid": "321", "x": "3496.06", "y": "3642.8", "width": "157", "height": "178", "fog_area": "51", "max_num": "1"}, {"id": "4000014", "name": "resource_point", "gid": "348", "x": "3375.33", "y": "4090.75", "width": "98", "height": "75", "fog_area": "51", "max_num": "1"}, {"id": "4000010", "name": "resource_point", "gid": "329", "x": "3872.46", "y": "3252.13", "width": "141", "height": "199", "fog_area": "57", "max_num": "1"}, {"id": "4000014", "name": "resource_point", "gid": "348", "x": "3900.74", "y": "3387.52", "width": "98", "height": "75", "fog_area": "57", "max_num": "1"}, {"id": "4000012", "name": "resource_point", "gid": "341", "x": "3593.64", "y": "2528.57", "width": "83", "height": "76", "fog_area": "54", "max_num": "1"}, {"id": "4000014", "name": "resource_point", "gid": "348", "x": "4168.31", "y": "2864.65", "width": "98", "height": "75", "fog_area": "57", "max_num": "1"}, {"id": "4000008", "name": "resource_point", "gid": "330", "x": "3901.39", "y": "2844.03", "width": "122", "height": "142", "fog_area": "57", "max_num": "1"}, {"id": "4000010", "name": "resource_point", "gid": "329", "x": "4199.26", "y": "2721.06", "width": "141", "height": "199", "fog_area": "57", "max_num": "1"}, {"id": "4000010", "name": "resource_point", "gid": "329", "x": "3370.29", "y": "1422.51", "width": "141", "height": "199", "fog_area": "54", "max_num": "1"}, {"id": "4000011", "name": "resource_point", "gid": "340", "x": "3099.29", "y": "1310.77", "width": "72", "height": "65", "fog_area": "54", "max_num": "1"}, {"id": "4000012", "name": "resource_point", "gid": "341", "x": "2176.89", "y": "1811.73", "width": "83", "height": "76", "fog_area": "54", "max_num": "1"}, {"id": "4000012", "name": "resource_point", "gid": "341", "x": "2501.75", "y": "1420.66", "width": "83", "height": "76", "fog_area": "54", "max_num": "1"}, {"id": "4000009", "name": "resource_point", "gid": "321", "x": "3106.93", "y": "1481.63", "width": "157", "height": "178", "fog_area": "54", "max_num": "1"}, {"id": "4000009", "name": "resource_point", "gid": "321", "x": "2512.03", "y": "1714.15", "width": "157", "height": "178", "fog_area": "54", "max_num": "1"}, {"id": "4000014", "name": "resource_point", "gid": "348", "x": "2514.45", "y": "1823.64", "width": "98", "height": "75", "fog_area": "54", "max_num": "1"}, {"id": "4000008", "name": "resource_point", "gid": "330", "x": "3593.31", "y": "2370.63", "width": "122", "height": "142", "fog_area": "55", "max_num": "1"}, {"id": "4000008", "name": "resource_point", "gid": "330", "x": "4056.08", "y": "2258.29", "width": "122", "height": "142", "fog_area": "55", "max_num": "1"}, {"id": "4000009", "name": "resource_point", "gid": "321", "x": "2729.6", "y": "1978.4", "width": "157", "height": "178", "fog_area": "54", "max_num": "1"}, {"id": "4000010", "name": "resource_point", "gid": "329", "x": "3727.64", "y": "2307", "width": "141", "height": "199", "fog_area": "55", "max_num": "1"}, {"id": "4000009", "name": "resource_point", "gid": "321", "x": "3760.13", "y": "1774.19", "width": "157", "height": "178", "fog_area": "55", "max_num": "1"}, {"id": "4000014", "name": "resource_point", "gid": "348", "x": "4104.28", "y": "2101.52", "width": "98", "height": "75", "fog_area": "55", "max_num": "1"}, {"id": "4000010", "name": "resource_point", "gid": "329", "x": "6617.08", "y": "3220.95", "width": "141", "height": "199", "fog_area": "56", "max_num": "1"}, {"id": "4000009", "name": "resource_point", "gid": "321", "x": "3566.15", "y": "1501.3", "width": "157", "height": "178", "fog_area": "55", "max_num": "1"}, {"id": "4000014", "name": "resource_point", "gid": "348", "x": "3634.31", "y": "1375.65", "width": "98", "height": "75", "fog_area": "55", "max_num": "1"}, {"id": "4000008", "name": "resource_point", "gid": "330", "x": "4176.39", "y": "1506.55", "width": "122", "height": "142", "fog_area": "55", "max_num": "1"}, {"id": "4000008", "name": "resource_point", "gid": "330", "x": "4642.86", "y": "1508.25", "width": "122", "height": "142", "fog_area": "55", "max_num": "1"}, {"id": "4000009", "name": "resource_point", "gid": "321", "x": "4332.39", "y": "1536.02", "width": "157", "height": "178", "fog_area": "55", "max_num": "1"}, {"id": "4000010", "name": "resource_point", "gid": "329", "x": "6505.87", "y": "2977.37", "width": "141", "height": "199", "fog_area": "56", "max_num": "1"}, {"id": "4000010", "name": "resource_point", "gid": "329", "x": "4734.86", "y": "2234.67", "width": "141", "height": "199", "fog_area": "55", "max_num": "1"}, {"id": "4000011", "name": "resource_point", "gid": "340", "x": "3797.47", "y": "1311.45", "width": "72", "height": "65", "fog_area": "55", "max_num": "1"}, {"id": "4000011", "name": "resource_point", "gid": "340", "x": "3982.63", "y": "1371.76", "width": "72", "height": "65", "fog_area": "55", "max_num": "1"}, {"id": "4000012", "name": "resource_point", "gid": "341", "x": "3988.76", "y": "1579.67", "width": "83", "height": "76", "fog_area": "55", "max_num": "1"}, {"id": "4000011", "name": "resource_point", "gid": "340", "x": "5079.14", "y": "1648.66", "width": "72", "height": "65", "fog_area": "55", "max_num": "1"}, {"id": "4000011", "name": "resource_point", "gid": "340", "x": "5263.15", "y": "1676.77", "width": "72", "height": "65", "fog_area": "55", "max_num": "1"}, {"id": "4000012", "name": "resource_point", "gid": "341", "x": "5192.04", "y": "1533.62", "width": "83", "height": "76", "fog_area": "55", "max_num": "1"}, {"id": "4000009", "name": "resource_point", "gid": "321", "x": "4362.16", "y": "2211.86", "width": "157", "height": "178", "fog_area": "55", "max_num": "1"}, {"id": "4000014", "name": "resource_point", "gid": "348", "x": "5425.87", "y": "1652.32", "width": "98", "height": "75", "fog_area": "55", "max_num": "1"}, {"id": "4000010", "name": "resource_point", "gid": "329", "x": "5055.36", "y": "1536.51", "width": "141", "height": "199", "fog_area": "55", "max_num": "1"}, {"id": "4000008", "name": "resource_point", "gid": "330", "x": "5833.97", "y": "2401.34", "width": "122", "height": "142", "fog_area": "56", "max_num": "1"}, {"id": "4000008", "name": "resource_point", "gid": "330", "x": "5735.49", "y": "1964.15", "width": "122", "height": "142", "fog_area": "55", "max_num": "1"}, {"id": "4000009", "name": "resource_point", "gid": "321", "x": "5263.77", "y": "2107.26", "width": "157", "height": "178", "fog_area": "55", "max_num": "1"}, {"id": "4000010", "name": "resource_point", "gid": "329", "x": "5955.76", "y": "2196.34", "width": "141", "height": "199", "fog_area": "56", "max_num": "1"}, {"id": "4000011", "name": "resource_point", "gid": "340", "x": "5986.93", "y": "2419.18", "width": "72", "height": "65", "fog_area": "56", "max_num": "1"}, {"id": "4000011", "name": "resource_point", "gid": "340", "x": "6257.41", "y": "2468.15", "width": "72", "height": "65", "fog_area": "56", "max_num": "1"}, {"id": "4000012", "name": "resource_point", "gid": "341", "x": "5917.4", "y": "2558.62", "width": "83", "height": "76", "fog_area": "56", "max_num": "1"}, {"id": "4000009", "name": "resource_point", "gid": "321", "x": "5694.75", "y": "2261.33", "width": "157", "height": "178", "fog_area": "56", "max_num": "1"}, {"id": "4000010", "name": "resource_point", "gid": "329", "x": "5852.41", "y": "2901.1", "width": "141", "height": "199", "fog_area": "56", "max_num": "1"}, {"id": "4000010", "name": "resource_point", "gid": "329", "x": "5231.8", "y": "2775.85", "width": "141", "height": "199", "fog_area": "56", "max_num": "1"}, {"id": "4000014", "name": "resource_point", "gid": "348", "x": "6714.76", "y": "3615.65", "width": "98", "height": "75", "fog_area": "56", "max_num": "1"}, {"id": "4000011", "name": "resource_point", "gid": "340", "x": "6587.54", "y": "3689.07", "width": "72", "height": "65", "fog_area": "56", "max_num": "1"}, {"id": "4000012", "name": "resource_point", "gid": "341", "x": "6826.73", "y": "3779.75", "width": "83", "height": "76", "fog_area": "56", "max_num": "1"}, {"id": "4000012", "name": "resource_point", "gid": "341", "x": "4695.86", "y": "3194.64", "width": "83", "height": "76", "fog_area": "57", "max_num": "1"}, {"id": "4000012", "name": "resource_point", "gid": "341", "x": "3520.85", "y": "3319.7", "width": "83", "height": "76", "fog_area": "54", "max_num": "1"}, {"id": "4000011", "name": "resource_point", "gid": "340", "x": "4386.99", "y": "4070.28", "width": "72", "height": "65", "fog_area": "57", "max_num": "1"}, {"id": "4000011", "name": "resource_point", "gid": "340", "x": "5264.9", "y": "3948.28", "width": "72", "height": "65", "fog_area": "57", "max_num": "1"}, {"id": "4000011", "name": "resource_point", "gid": "340", "x": "5373.84", "y": "4067.3", "width": "72", "height": "65", "fog_area": "57", "max_num": "1"}, {"id": "4000012", "name": "resource_point", "gid": "341", "x": "5577.47", "y": "4011.87", "width": "83", "height": "76", "fog_area": "58", "max_num": "1"}, {"id": "4000012", "name": "resource_point", "gid": "341", "x": "6230.23", "y": "4600.79", "width": "84.3731", "height": "77.2573", "fog_area": "58", "max_num": "1"}, {"id": "4000011", "name": "resource_point", "gid": "340", "x": "6198.13", "y": "4420.68", "width": "73.1911", "height": "66.0753", "fog_area": "58", "max_num": "1"}, {"id": "4000011", "name": "resource_point", "gid": "340", "x": "6992.89", "y": "4823.1", "width": "73.3333", "height": "70.3333", "fog_area": "58", "max_num": "1"}, {"id": "4000011", "name": "resource_point", "gid": "340", "x": "6836.63", "y": "4794.23", "width": "72", "height": "65", "fog_area": "58", "max_num": "1"}, {"id": "4000008", "name": "resource_point", "gid": "330", "x": "4821.42", "y": "2458.7", "width": "122", "height": "142", "fog_area": "55", "max_num": "1"}, {"id": "4000014", "name": "resource_point", "gid": "348", "x": "5284.1", "y": "2946.52", "width": "98", "height": "75", "fog_area": "56", "max_num": "1"}, {"id": "4000010", "name": "resource_point", "gid": "329", "x": "5436.44", "y": "3205.85", "width": "141", "height": "199", "fog_area": "56", "max_num": "1"}, {"id": "4000009", "name": "resource_point", "gid": "321", "x": "5702.84", "y": "3013.32", "width": "157", "height": "178", "fog_area": "56", "max_num": "1"}, {"id": "4000008", "name": "resource_point", "gid": "330", "x": "5718.69", "y": "3152.54", "width": "122", "height": "142", "fog_area": "56", "max_num": "1"}, {"id": "4000008", "name": "resource_point", "gid": "330", "x": "4156.2", "y": "3815.15", "width": "122", "height": "142", "fog_area": "57", "max_num": "1"}, {"id": "4000009", "name": "resource_point", "gid": "321", "x": "4913.8", "y": "4313.86", "width": "157", "height": "178", "fog_area": "57", "max_num": "1"}, {"id": "4000010", "name": "resource_point", "gid": "329", "x": "5397.04", "y": "3844.63", "width": "141", "height": "199", "fog_area": "57", "max_num": "1"}, {"id": "4000010", "name": "resource_point", "gid": "329", "x": "6110.93", "y": "4140.44", "width": "143.333", "height": "202.292", "fog_area": "58", "max_num": "1"}, {"id": "4000009", "name": "resource_point", "gid": "321", "x": "7021.8", "y": "3732.75", "width": "157", "height": "178", "fog_area": "56", "max_num": "1"}, {"id": "4000014", "name": "resource_point", "gid": "348", "x": "5881.27", "y": "4163.48", "width": "98", "height": "75", "fog_area": "58", "max_num": "1"}, {"id": "4000009", "name": "resource_point", "gid": "321", "x": "6042.01", "y": "3918.74", "width": "157", "height": "178", "fog_area": "58", "max_num": "1"}, {"id": "4000014", "name": "resource_point", "gid": "348", "x": "5486.67", "y": "4114.67", "width": "98", "height": "75", "fog_area": "58", "max_num": "1"}, {"id": "4000008", "name": "resource_point", "gid": "330", "x": "6386.34", "y": "4630.26", "width": "122", "height": "142", "fog_area": "58", "max_num": "1"}, {"id": "4000009", "name": "resource_point", "gid": "321", "x": "6824.21", "y": "4156.13", "width": "157", "height": "178", "fog_area": "58", "max_num": "1"}, {"id": "4000008", "name": "resource_point", "gid": "330", "x": "6791.58", "y": "4300.91", "width": "122", "height": "142", "fog_area": "58", "max_num": "1"}, {"id": "4000010", "name": "resource_point", "gid": "329", "x": "7167.91", "y": "4294.34", "width": "141", "height": "199", "fog_area": "58", "max_num": "1"}, {"id": "4000009", "name": "resource_point", "gid": "321", "x": "6963.68", "y": "5126.29", "width": "157", "height": "178", "fog_area": "58", "max_num": "1"}, {"id": "4000009", "name": "resource_point", "gid": "321", "x": "5499.88", "y": "3428.2", "width": "157", "height": "178", "fog_area": "56", "max_num": "1"}, {"id": "4000011", "name": "resource_point", "gid": "340", "x": "3260.81", "y": "5203.9", "width": "72", "height": "65", "fog_area": "51", "max_num": "1"}, {"id": "4000008", "name": "resource_point", "gid": "330", "x": "2906.37", "y": "5361.76", "width": "122", "height": "142", "fog_area": "51", "max_num": "1"}], "monster_point": [{"id": "7000908", "name": "monster_point", "gid": "311", "x": "3126.63", "y": "4323.65", "width": "313", "height": "217", "fog_area": "51", "max_num": "1"}, {"id": "7000047", "name": "monster_point", "gid": "300", "x": "2958.87", "y": "2741.89", "width": "58", "height": "81", "fog_area": "54", "max_num": "3"}, {"id": "7000047", "name": "monster_point", "gid": "300", "x": "2951.2", "y": "3627.4", "width": "58", "height": "81", "fog_area": "51", "max_num": "3"}, {"id": "7000047", "name": "monster_point", "gid": "300", "x": "2497.24", "y": "1893.73", "width": "58", "height": "81", "fog_area": "54", "max_num": "3"}, {"id": "7000050", "name": "monster_point", "gid": "298", "x": "3486.35", "y": "2977.1", "width": "69", "height": "81", "fog_area": "54", "max_num": "5"}, {"id": "7000049", "name": "monster_point", "gid": "286", "x": "2491.7", "y": "2778.31", "width": "65", "height": "65", "fog_area": "54", "max_num": "3"}, {"id": "7000048", "name": "monster_point", "gid": "299", "x": "2868.98", "y": "1685.42", "width": "81", "height": "81", "fog_area": "54", "max_num": "3"}, {"id": "7000050", "name": "monster_point", "gid": "298", "x": "2936.51", "y": "2224.98", "width": "69", "height": "81", "fog_area": "54", "max_num": "5"}, {"id": "7000047", "name": "monster_point", "gid": "300", "x": "3785.82", "y": "1513.89", "width": "58", "height": "81", "fog_area": "55", "max_num": "3"}, {"id": "7000047", "name": "monster_point", "gid": "300", "x": "4612.61", "y": "2240.31", "width": "58", "height": "81", "fog_area": "55", "max_num": "3"}, {"id": "7000049", "name": "monster_point", "gid": "286", "x": "3857.11", "y": "2109.04", "width": "65", "height": "65", "fog_area": "55", "max_num": "3"}, {"id": "7000049", "name": "monster_point", "gid": "286", "x": "5437.9", "y": "1848.74", "width": "65", "height": "65", "fog_area": "55", "max_num": "3"}, {"id": "7000050", "name": "monster_point", "gid": "298", "x": "3221.5", "y": "1559.5", "width": "69", "height": "81", "fog_area": "54", "max_num": "3"}, {"id": "7000050", "name": "monster_point", "gid": "298", "x": "4225.5", "y": "1879.5", "width": "69", "height": "81", "fog_area": "55", "max_num": "5"}, {"id": "7000050", "name": "monster_point", "gid": "298", "x": "2411.5", "y": "2705.5", "width": "69", "height": "81", "fog_area": "54", "max_num": "2"}, {"id": "7000049", "name": "monster_point", "gid": "286", "x": "4592.7", "y": "1650.3", "width": "65", "height": "65", "fog_area": "55", "max_num": "3"}, {"id": "7000049", "name": "monster_point", "gid": "286", "x": "3410.7", "y": "2412.3", "width": "65", "height": "65", "fog_area": "54", "max_num": "3"}, {"id": "7000050", "name": "monster_point", "gid": "298", "x": "5058.7", "y": "1882.3", "width": "69", "height": "81", "fog_area": "55", "max_num": "5"}, {"id": "7000048", "name": "monster_point", "gid": "299", "x": "4915.5", "y": "2419.5", "width": "81", "height": "81", "fog_area": "55", "max_num": "3"}, {"id": "7000047", "name": "monster_point", "gid": "300", "x": "5761", "y": "3415.11", "width": "58", "height": "81", "fog_area": "56", "max_num": "3"}, {"id": "7000049", "name": "monster_point", "gid": "286", "x": "6184.31", "y": "2665.04", "width": "65", "height": "65", "fog_area": "56", "max_num": "3"}, {"id": "7000050", "name": "monster_point", "gid": "298", "x": "5574.3", "y": "2805.9", "width": "69", "height": "81", "fog_area": "56", "max_num": "5"}, {"id": "7000048", "name": "monster_point", "gid": "299", "x": "6470.7", "y": "3343.5", "width": "81", "height": "81", "fog_area": "56", "max_num": "3"}, {"id": "7000050", "name": "monster_point", "gid": "298", "x": "6365.9", "y": "3223.1", "width": "69", "height": "81", "fog_area": "56", "max_num": "2"}, {"id": "7000050", "name": "monster_point", "gid": "298", "x": "5629.9", "y": "3531.1", "width": "69", "height": "81", "fog_area": "56", "max_num": "2"}, {"id": "7000047", "name": "monster_point", "gid": "300", "x": "5929.4", "y": "3045.1", "width": "58", "height": "81", "fog_area": "56", "max_num": "1"}, {"id": "7000047", "name": "monster_point", "gid": "300", "x": "6105.4", "y": "2573.1", "width": "58", "height": "81", "fog_area": "56", "max_num": "2"}, {"id": "7000050", "name": "monster_point", "gid": "298", "x": "4215.1", "y": "3229.9", "width": "69", "height": "81", "fog_area": "57", "max_num": "2"}, {"id": "7000047", "name": "monster_point", "gid": "300", "x": "4431.05", "y": "3800.13", "width": "58", "height": "81", "fog_area": "57", "max_num": "3"}, {"id": "7000049", "name": "monster_point", "gid": "286", "x": "4827.16", "y": "3397.27", "width": "65", "height": "65", "fog_area": "57", "max_num": "3"}, {"id": "7000048", "name": "monster_point", "gid": "299", "x": "4863.95", "y": "3953.32", "width": "81", "height": "81", "fog_area": "57", "max_num": "3"}, {"id": "7000050", "name": "monster_point", "gid": "298", "x": "6768.49", "y": "4871.66", "width": "69", "height": "81", "fog_area": "58", "max_num": "3"}, {"id": "7000909", "name": "monster_point", "gid": "311", "x": "6518.75", "y": "5337.58", "width": "313", "height": "217", "fog_area": "58", "max_num": "1"}, {"id": "7000049", "name": "monster_point", "gid": "286", "x": "7067.6", "y": "4412.98", "width": "65", "height": "65", "fog_area": "58", "max_num": "5"}, {"id": "7000048", "name": "monster_point", "gid": "299", "x": "5999.56", "y": "4388.65", "width": "81", "height": "81", "fog_area": "58", "max_num": "3"}, {"id": "7000050", "name": "monster_point", "gid": "298", "x": "5969.23", "y": "4883.16", "width": "69", "height": "81", "fog_area": "58", "max_num": "2"}, {"id": "7000047", "name": "monster_point", "gid": "300", "x": "7125.64", "y": "4477.71", "width": "58", "height": "81", "fog_area": "58", "max_num": "2"}, {"id": "7000049", "name": "monster_point", "gid": "286", "x": "6019.11", "y": "4255.4", "width": "65", "height": "65", "fog_area": "58", "max_num": "2"}, {"id": "7000043", "name": "monster_point", "gid": "283", "x": "3905.8", "y": "5104.19", "width": "57", "height": "69", "fog_area": "49", "max_num": "3"}, {"id": "7000045", "name": "monster_point", "gid": "280", "x": "3638.25", "y": "5218.28", "width": "83", "height": "59", "fog_area": "49", "max_num": "2"}, {"id": "7000046", "name": "monster_point", "gid": "294", "x": "3425.25", "y": "4772.74", "width": "69", "height": "81", "fog_area": "51", "max_num": "5"}, {"id": "7000046", "name": "monster_point", "gid": "294", "x": "2864.4", "y": "5003.52", "width": "69", "height": "81", "fog_area": "51", "max_num": "5"}]}