{"resource_point": [{"id": "4000018", "name": "resource_point", "gid": "352", "x": "9792.74", "y": "2903.16", "width": "114", "height": "172", "fog_area": "70", "max_num": "1"}, {"id": "4000015", "name": "resource_point", "gid": "349", "x": "9489.84", "y": "2826.6", "width": "105", "height": "82", "fog_area": "70", "max_num": "1"}, {"id": "4000017", "name": "resource_point", "gid": "351", "x": "9807.54", "y": "3061.27", "width": "67", "height": "131", "fog_area": "70", "max_num": "1"}, {"id": "4000018", "name": "resource_point", "gid": "352", "x": "9808.65", "y": "4090.86", "width": "114", "height": "172", "fog_area": "67", "max_num": "1"}, {"id": "4000017", "name": "resource_point", "gid": "351", "x": "9895.13", "y": "4264.15", "width": "67", "height": "131", "fog_area": "67", "max_num": "1"}, {"id": "4000017", "name": "resource_point", "gid": "351", "x": "8813.27", "y": "4436.46", "width": "67", "height": "131", "fog_area": "67", "max_num": "1"}, {"id": "4000016", "name": "resource_point", "gid": "350", "x": "8938.81", "y": "4685.92", "width": "91", "height": "161", "fog_area": "67", "max_num": "1"}, {"id": "4000018", "name": "resource_point", "gid": "352", "x": "8747.53", "y": "3447.03", "width": "114", "height": "172", "fog_area": "67", "max_num": "1"}, {"id": "4000015", "name": "resource_point", "gid": "349", "x": "8760.12", "y": "3583.09", "width": "105", "height": "82", "fog_area": "67", "max_num": "1"}, {"id": "4000017", "name": "resource_point", "gid": "351", "x": "8923.41", "y": "3469.14", "width": "67", "height": "131", "fog_area": "67", "max_num": "1"}, {"id": "4000015", "name": "resource_point", "gid": "349", "x": "9067.05", "y": "4257.09", "width": "105", "height": "82", "fog_area": "67", "max_num": "1"}, {"id": "4000017", "name": "resource_point", "gid": "351", "x": "9360.96", "y": "4572.69", "width": "67", "height": "131", "fog_area": "67", "max_num": "1"}, {"id": "4000016", "name": "resource_point", "gid": "350", "x": "9283.28", "y": "4312.74", "width": "91", "height": "161", "fog_area": "67", "max_num": "1"}, {"id": "4000016", "name": "resource_point", "gid": "350", "x": "8862.92", "y": "2862.78", "width": "91", "height": "161", "fog_area": "68", "max_num": "1"}, {"id": "4000018", "name": "resource_point", "gid": "352", "x": "9101.28", "y": "2940.64", "width": "114", "height": "172", "fog_area": "68", "max_num": "1"}, {"id": "4000015", "name": "resource_point", "gid": "349", "x": "7983.28", "y": "2110.07", "width": "105", "height": "82", "fog_area": "68", "max_num": "1"}, {"id": "4000018", "name": "resource_point", "gid": "352", "x": "8134.68", "y": "2323.91", "width": "114", "height": "172", "fog_area": "68", "max_num": "1"}, {"id": "4000017", "name": "resource_point", "gid": "351", "x": "7890.71", "y": "2243.79", "width": "67", "height": "131", "fog_area": "68", "max_num": "1"}, {"id": "4000015", "name": "resource_point", "gid": "349", "x": "9627.49", "y": "2066.92", "width": "105", "height": "82", "fog_area": "69", "max_num": "1"}, {"id": "4000016", "name": "resource_point", "gid": "350", "x": "9279.66", "y": "1935.49", "width": "91", "height": "161", "fog_area": "68", "max_num": "1"}, {"id": "4000018", "name": "resource_point", "gid": "352", "x": "9384.45", "y": "2162.67", "width": "114", "height": "172", "fog_area": "69", "max_num": "1"}, {"id": "4000017", "name": "resource_point", "gid": "351", "x": "9678.95", "y": "1942.3", "width": "67", "height": "131", "fog_area": "69", "max_num": "1"}, {"id": "4000016", "name": "resource_point", "gid": "350", "x": "10275.2", "y": "4121.46", "width": "91", "height": "161", "fog_area": "70", "max_num": "1"}, {"id": "4000016", "name": "resource_point", "gid": "350", "x": "10834", "y": "2630.63", "width": "91", "height": "161", "fog_area": "70", "max_num": "1"}, {"id": "4000016", "name": "resource_point", "gid": "350", "x": "10384.5", "y": "2783.58", "width": "91", "height": "161", "fog_area": "70", "max_num": "1"}, {"id": "4000015", "name": "resource_point", "gid": "349", "x": "10533.9", "y": "2958.93", "width": "105", "height": "82", "fog_area": "70", "max_num": "1"}, {"id": "4000017", "name": "resource_point", "gid": "351", "x": "11001.3", "y": "2726.16", "width": "67", "height": "131", "fog_area": "70", "max_num": "1"}, {"id": "4000018", "name": "resource_point", "gid": "352", "x": "10440.9", "y": "3722.3", "width": "114", "height": "172", "fog_area": "70", "max_num": "1"}, {"id": "4000018", "name": "resource_point", "gid": "352", "x": "9285.02", "y": "2212", "width": "114", "height": "172", "fog_area": "68", "max_num": "1"}, {"id": "4000017", "name": "resource_point", "gid": "351", "x": "9979.03", "y": "3731.46", "width": "67", "height": "131", "fog_area": "70", "max_num": "1"}, {"id": "4000016", "name": "resource_point", "gid": "350", "x": "10237.1", "y": "3730.65", "width": "91", "height": "161", "fog_area": "70", "max_num": "1"}, {"id": "4000018", "name": "resource_point", "gid": "352", "x": "10603.3", "y": "4659.08", "width": "114", "height": "172", "fog_area": "67", "max_num": "1"}, {"id": "4000015", "name": "resource_point", "gid": "349", "x": "10294.8", "y": "4620.12", "width": "105", "height": "82", "fog_area": "67", "max_num": "1"}, {"id": "4000017", "name": "resource_point", "gid": "351", "x": "10612.5", "y": "4854.79", "width": "67", "height": "131", "fog_area": "67", "max_num": "1"}, {"id": "4000015", "name": "resource_point", "gid": "349", "x": "10882.9", "y": "4857.67", "width": "105", "height": "82", "fog_area": "67", "max_num": "1"}, {"id": "4000016", "name": "resource_point", "gid": "350", "x": "10788.2", "y": "4109.86", "width": "91", "height": "161", "fog_area": "70", "max_num": "1"}, {"id": "4000017", "name": "resource_point", "gid": "351", "x": "10796.6", "y": "4680.16", "width": "67", "height": "131", "fog_area": "67", "max_num": "1"}, {"id": "4000018", "name": "resource_point", "gid": "352", "x": "11338.3", "y": "4847.99", "width": "114", "height": "172", "fog_area": "70", "max_num": "1"}, {"id": "4000016", "name": "resource_point", "gid": "350", "x": "11647.1", "y": "5077.9", "width": "91", "height": "161", "fog_area": "70", "max_num": "1"}, {"id": "4000017", "name": "resource_point", "gid": "351", "x": "11927.7", "y": "5176.26", "width": "67", "height": "131", "fog_area": "70", "max_num": "1"}, {"id": "4000015", "name": "resource_point", "gid": "349", "x": "11433", "y": "4787.56", "width": "105", "height": "82", "fog_area": "70", "max_num": "1"}, {"id": "4000018", "name": "resource_point", "gid": "352", "x": "11758.5", "y": "3428.09", "width": "114", "height": "172", "fog_area": "70", "max_num": "1"}, {"id": "4000015", "name": "resource_point", "gid": "349", "x": "11772.6", "y": "4128.06", "width": "105", "height": "82", "fog_area": "70", "max_num": "1"}, {"id": "4000017", "name": "resource_point", "gid": "351", "x": "11915.1", "y": "3484.45", "width": "67", "height": "131", "fog_area": "70", "max_num": "1"}, {"id": "4000016", "name": "resource_point", "gid": "350", "x": "10689.7", "y": "3754.15", "width": "91", "height": "161", "fog_area": "70", "max_num": "1"}, {"id": "4000018", "name": "resource_point", "gid": "352", "x": "8602.57", "y": "2234.49", "width": "114", "height": "172", "fog_area": "68", "max_num": "1"}, {"id": "4000017", "name": "resource_point", "gid": "351", "x": "8618.67", "y": "1950.8", "width": "67", "height": "131", "fog_area": "68", "max_num": "1"}, {"id": "4000017", "name": "resource_point", "gid": "351", "x": "12606.4", "y": "4657.6", "width": "67", "height": "131", "fog_area": "71", "max_num": "1"}, {"id": "4000015", "name": "resource_point", "gid": "349", "x": "12561.4", "y": "5422.14", "width": "105", "height": "82", "fog_area": "71", "max_num": "1"}, {"id": "4000018", "name": "resource_point", "gid": "352", "x": "12299.3", "y": "5040", "width": "114", "height": "172", "fog_area": "70", "max_num": "1"}, {"id": "4000018", "name": "resource_point", "gid": "352", "x": "12600", "y": "5160", "width": "114", "height": "172", "fog_area": "71", "max_num": "1"}, {"id": "4000015", "name": "resource_point", "gid": "349", "x": "12096.7", "y": "4877.43", "width": "105", "height": "82", "fog_area": "70", "max_num": "1"}, {"id": "4000017", "name": "resource_point", "gid": "351", "x": "12517.3", "y": "4717.87", "width": "67", "height": "131", "fog_area": "71", "max_num": "1"}, {"id": "4000016", "name": "resource_point", "gid": "350", "x": "13320.2", "y": "4989.68", "width": "91", "height": "161", "fog_area": "71", "max_num": "1"}, {"id": "4000015", "name": "resource_point", "gid": "349", "x": "13446.9", "y": "4965.02", "width": "105", "height": "82", "fog_area": "71", "max_num": "1"}, {"id": "4000017", "name": "resource_point", "gid": "351", "x": "13599.4", "y": "5187.38", "width": "67", "height": "131", "fog_area": "71", "max_num": "1"}, {"id": "4000017", "name": "resource_point", "gid": "351", "x": "12336.5", "y": "3621.87", "width": "70.2806", "height": "137.414", "fog_area": "70", "max_num": "1"}, {"id": "4000017", "name": "resource_point", "gid": "351", "x": "12709", "y": "2763.57", "width": "67", "height": "131", "fog_area": "71", "max_num": "1"}, {"id": "4000015", "name": "resource_point", "gid": "349", "x": "12741.8", "y": "2927.92", "width": "105", "height": "82", "fog_area": "71", "max_num": "1"}, {"id": "4000018", "name": "resource_point", "gid": "352", "x": "13505.8", "y": "3493.31", "width": "114", "height": "172", "fog_area": "71", "max_num": "1"}, {"id": "4000018", "name": "resource_point", "gid": "350", "x": "13377.3", "y": "3508.1", "width": "91", "height": "161", "fog_area": "71", "max_num": "1"}, {"id": "4000015", "name": "resource_point", "gid": "349", "x": "13800", "y": "3600", "width": "105", "height": "82", "fog_area": "71", "max_num": "1"}, {"id": "4000017", "name": "resource_point", "gid": "351", "x": "13397.9", "y": "2632.92", "width": "67", "height": "131", "fog_area": "71", "max_num": "1"}, {"id": "4000018", "name": "resource_point", "gid": "352", "x": "13286.2", "y": "2672.05", "width": "114", "height": "172", "fog_area": "71", "max_num": "1"}, {"id": "4000016", "name": "resource_point", "gid": "350", "x": "13681.5", "y": "3354.68", "width": "91", "height": "161", "fog_area": "71", "max_num": "1"}, {"id": "4000016", "name": "resource_point", "gid": "350", "x": "9618.56", "y": "3237.64", "width": "91", "height": "161", "fog_area": "70", "max_num": "1"}, {"id": "4000018", "name": "resource_point", "gid": "352", "x": "9614.46", "y": "3394.59", "width": "114", "height": "172", "fog_area": "70", "max_num": "1"}, {"id": "4000015", "name": "resource_point", "gid": "349", "x": "12290.8", "y": "3742.79", "width": "105", "height": "82", "fog_area": "70", "max_num": "1"}, {"id": "4000016", "name": "resource_point", "gid": "350", "x": "11554.7", "y": "2701.96", "width": "91", "height": "161", "fog_area": "70", "max_num": "1"}, {"id": "4000015", "name": "resource_point", "gid": "349", "x": "11652", "y": "2899.66", "width": "105", "height": "82", "fog_area": "70", "max_num": "1"}, {"id": "4000018", "name": "resource_point", "gid": "352", "x": "11499", "y": "2878.12", "width": "114", "height": "172", "fog_area": "70", "max_num": "1"}, {"id": "4000016", "name": "resource_point", "gid": "350", "x": "11869.2", "y": "2598.5", "width": "91", "height": "161", "fog_area": "70", "max_num": "1"}, {"id": "4000017", "name": "resource_point", "gid": "351", "x": "12061.6", "y": "2623.09", "width": "67", "height": "131", "fog_area": "70", "max_num": "1"}, {"id": "4000015", "name": "resource_point", "gid": "349", "x": "12014.5", "y": "2485.29", "width": "105", "height": "82", "fog_area": "69", "max_num": "1"}, {"id": "4000018", "name": "resource_point", "gid": "352", "x": "11135.2", "y": "2291.66", "width": "114", "height": "172", "fog_area": "69", "max_num": "1"}, {"id": "4000017", "name": "resource_point", "gid": "351", "x": "10946.5", "y": "2352.72", "width": "67", "height": "131", "fog_area": "69", "max_num": "1"}, {"id": "4000015", "name": "resource_point", "gid": "349", "x": "10894.9", "y": "2222.41", "width": "105", "height": "82", "fog_area": "69", "max_num": "1"}, {"id": "4000017", "name": "resource_point", "gid": "351", "x": "12564.4", "y": "2876.68", "width": "67", "height": "131", "fog_area": "71", "max_num": "1"}, {"id": "4000015", "name": "resource_point", "gid": "349", "x": "12550.4", "y": "3751.3", "width": "110.141", "height": "86.0151", "fog_area": "71", "max_num": "1"}, {"id": "4000012", "name": "resource_point", "gid": "341", "x": "8868.75", "y": "4251.97", "width": "83", "height": "76", "fog_area": "67", "max_num": "1"}, {"id": "4000012", "name": "resource_point", "gid": "341", "x": "8554.3", "y": "4070.12", "width": "83", "height": "76", "fog_area": "67", "max_num": "1"}, {"id": "4000011", "name": "resource_point", "gid": "340", "x": "8397.26", "y": "4055.42", "width": "72", "height": "65", "fog_area": "67", "max_num": "1"}, {"id": "4000011", "name": "resource_point", "gid": "340", "x": "9681.31", "y": "4460.11", "width": "72", "height": "65", "fog_area": "67", "max_num": "1"}, {"id": "4000011", "name": "resource_point", "gid": "340", "x": "9865.96", "y": "4371.35", "width": "72", "height": "65", "fog_area": "67", "max_num": "1"}, {"id": "4000012", "name": "resource_point", "gid": "341", "x": "9675.94", "y": "4207.61", "width": "83", "height": "76", "fog_area": "67", "max_num": "1"}, {"id": "4000012", "name": "resource_point", "gid": "341", "x": "8133.98", "y": "2611.35", "width": "83", "height": "76", "fog_area": "68", "max_num": "1"}, {"id": "4000011", "name": "resource_point", "gid": "340", "x": "7917.87", "y": "2724.75", "width": "72", "height": "65", "fog_area": "68", "max_num": "1"}, {"id": "4000011", "name": "resource_point", "gid": "340", "x": "8033.85", "y": "2477.17", "width": "72", "height": "65", "fog_area": "68", "max_num": "1"}, {"id": "4000011", "name": "resource_point", "gid": "340", "x": "8126.46", "y": "2196.51", "width": "72", "height": "65", "fog_area": "68", "max_num": "1"}, {"id": "4000011", "name": "resource_point", "gid": "340", "x": "10468.8", "y": "2577.19", "width": "72", "height": "65", "fog_area": "70", "max_num": "1"}, {"id": "4000012", "name": "resource_point", "gid": "341", "x": "10295", "y": "2553.59", "width": "83", "height": "76", "fog_area": "70", "max_num": "1"}, {"id": "4000011", "name": "resource_point", "gid": "340", "x": "10577.8", "y": "2731.69", "width": "72", "height": "65", "fog_area": "70", "max_num": "1"}, {"id": "4000011", "name": "resource_point", "gid": "340", "x": "10544.5", "y": "3139.33", "width": "72", "height": "65", "fog_area": "70", "max_num": "1"}, {"id": "4000012", "name": "resource_point", "gid": "341", "x": "10612.8", "y": "3267.56", "width": "83", "height": "76", "fog_area": "70", "max_num": "1"}, {"id": "4000012", "name": "resource_point", "gid": "341", "x": "11671.3", "y": "3015.91", "width": "83", "height": "76", "fog_area": "70", "max_num": "1"}, {"id": "4000011", "name": "resource_point", "gid": "340", "x": "11543.2", "y": "3032.55", "width": "72", "height": "65", "fog_area": "70", "max_num": "1"}, {"id": "4000011", "name": "resource_point", "gid": "340", "x": "11804.7", "y": "3149.1", "width": "72", "height": "65", "fog_area": "70", "max_num": "1"}, {"id": "4000011", "name": "resource_point", "gid": "340", "x": "14068.3", "y": "5188.47", "width": "72", "height": "65", "fog_area": "72", "max_num": "1"}, {"id": "4000012", "name": "resource_point", "gid": "341", "x": "13074.1", "y": "5348.44", "width": "83", "height": "76", "fog_area": "71", "max_num": "1"}, {"id": "4000012", "name": "resource_point", "gid": "341", "x": "13080", "y": "5520", "width": "83", "height": "76", "fog_area": "71", "max_num": "1"}, {"id": "4000011", "name": "resource_point", "gid": "340", "x": "12873.4", "y": "5200.04", "width": "72", "height": "65", "fog_area": "71", "max_num": "1"}, {"id": "4000015", "name": "resource_point", "gid": "349", "x": "12120", "y": "5052.58", "width": "105", "height": "82", "fog_area": "70", "max_num": "1"}, {"id": "4000011", "name": "resource_point", "gid": "340", "x": "13731", "y": "5349.68", "width": "72", "height": "65", "fog_area": "71", "max_num": "1"}, {"id": "4000011", "name": "resource_point", "gid": "340", "x": "13934.6", "y": "5510.09", "width": "72", "height": "65", "fog_area": "71", "max_num": "1"}, {"id": "4000012", "name": "resource_point", "gid": "341", "x": "14005.7", "y": "5055.42", "width": "83", "height": "76", "fog_area": "71", "max_num": "1"}, {"id": "4000011", "name": "resource_point", "gid": "340", "x": "12577.4", "y": "4153.2", "width": "72", "height": "65", "fog_area": "71", "max_num": "1"}, {"id": "4000012", "name": "resource_point", "gid": "341", "x": "12667.8", "y": "4045.61", "width": "83", "height": "76", "fog_area": "71", "max_num": "1"}, {"id": "4000012", "name": "resource_point", "gid": "341", "x": "12718.7", "y": "2571.81", "width": "83", "height": "76", "fog_area": "71", "max_num": "1"}, {"id": "4000012", "name": "resource_point", "gid": "341", "x": "13075.9", "y": "2509.74", "width": "83", "height": "76", "fog_area": "71", "max_num": "1"}, {"id": "4000012", "name": "resource_point", "gid": "341", "x": "12815.2", "y": "2506.49", "width": "83", "height": "76", "fog_area": "71", "max_num": "1"}, {"id": "4000011", "name": "resource_point", "gid": "340", "x": "12838.2", "y": "3009.26", "width": "72", "height": "65", "fog_area": "71", "max_num": "1"}, {"id": "4000012", "name": "resource_point", "gid": "341", "x": "12735.1", "y": "3063.16", "width": "83", "height": "76", "fog_area": "71", "max_num": "1"}, {"id": "4000012", "name": "resource_point", "gid": "341", "x": "12500.8", "y": "2989.72", "width": "83", "height": "76", "fog_area": "71", "max_num": "1"}, {"id": "4000012", "name": "resource_point", "gid": "341", "x": "13925.9", "y": "3988.55", "width": "83", "height": "76", "fog_area": "71", "max_num": "1"}, {"id": "4000011", "name": "resource_point", "gid": "340", "x": "13805.7", "y": "4045.5", "width": "72", "height": "65", "fog_area": "71", "max_num": "1"}, {"id": "4000011", "name": "resource_point", "gid": "340", "x": "13457", "y": "2838", "width": "72", "height": "65", "fog_area": "71", "max_num": "1"}, {"id": "4000011", "name": "resource_point", "gid": "340", "x": "13197.5", "y": "3682.74", "width": "72", "height": "65", "fog_area": "71", "max_num": "1"}, {"id": "4000012", "name": "resource_point", "gid": "341", "x": "13246.8", "y": "3608.72", "width": "83", "height": "76", "fog_area": "71", "max_num": "1"}, {"id": "4000011", "name": "resource_point", "gid": "340", "x": "9755.8", "y": "3253.56", "width": "72", "height": "65", "fog_area": "70", "max_num": "1"}, {"id": "4000011", "name": "resource_point", "gid": "340", "x": "9928.2", "y": "3413.06", "width": "72", "height": "65", "fog_area": "70", "max_num": "1"}, {"id": "4000012", "name": "resource_point", "gid": "341", "x": "11910", "y": "4374.56", "width": "83", "height": "76", "fog_area": "70", "max_num": "1"}, {"id": "4000011", "name": "resource_point", "gid": "340", "x": "11851.4", "y": "4214.98", "width": "72", "height": "65", "fog_area": "70", "max_num": "1"}, {"id": "4000011", "name": "resource_point", "gid": "340", "x": "11056.7", "y": "4687.82", "width": "72", "height": "65", "fog_area": "70", "max_num": "1"}, {"id": "4000011", "name": "resource_point", "gid": "340", "x": "10974.8", "y": "4833.81", "width": "72", "height": "65", "fog_area": "70", "max_num": "1"}, {"id": "4000011", "name": "resource_point", "gid": "340", "x": "11860.2", "y": "4532.86", "width": "72", "height": "65", "fog_area": "70", "max_num": "1"}, {"id": "4000016", "name": "resource_point", "gid": "350", "x": "12025.3", "y": "3396.97", "width": "91", "height": "161", "fog_area": "70", "max_num": "1"}, {"id": "4000016", "name": "resource_point", "gid": "350", "x": "8976.11", "y": "4439.27", "width": "91", "height": "161", "fog_area": "67", "max_num": "1"}, {"id": "4000017", "name": "resource_point", "gid": "351", "x": "9259.34", "y": "4658.83", "width": "67", "height": "131", "fog_area": "67", "max_num": "1"}, {"id": "4000016", "name": "resource_point", "gid": "350", "x": "9801.87", "y": "4662.18", "width": "91", "height": "161", "fog_area": "67", "max_num": "1"}, {"id": "4000016", "name": "resource_point", "gid": "350", "x": "10520.5", "y": "4137.5", "width": "91", "height": "161", "fog_area": "70", "max_num": "1"}, {"id": "4000016", "name": "resource_point", "gid": "350", "x": "9984.01", "y": "1346.53", "width": "91", "height": "161", "fog_area": "69", "max_num": "1"}, {"id": "4000018", "name": "resource_point", "gid": "352", "x": "10294.7", "y": "1492.29", "width": "114", "height": "172", "fog_area": "69", "max_num": "1"}, {"id": "4000018", "name": "resource_point", "gid": "352", "x": "10246", "y": "1200.09", "width": "114", "height": "172", "fog_area": "69", "max_num": "1"}, {"id": "4000017", "name": "resource_point", "gid": "351", "x": "10075.5", "y": "1236.22", "width": "67", "height": "131", "fog_area": "69", "max_num": "1"}], "monster_point": [{"id": "7000911", "name": "monster_point", "gid": "312", "x": "13736.7", "y": "4751.32", "width": "363", "height": "261", "fog_area": "71", "max_num": "1"}, {"id": "7000055", "name": "monster_point", "gid": "287", "x": "9491.29", "y": "4227.68", "width": "65", "height": "72", "fog_area": "67", "max_num": "3"}, {"id": "7000055", "name": "monster_point", "gid": "287", "x": "10389.6", "y": "4602.48", "width": "65", "height": "72", "fog_area": "67", "max_num": "3"}, {"id": "7000055", "name": "monster_point", "gid": "287", "x": "8335.05", "y": "3584.3", "width": "65", "height": "72", "fog_area": "67", "max_num": "3"}, {"id": "7000056", "name": "monster_point", "gid": "298", "x": "9098.69", "y": "3620.66", "width": "69", "height": "81", "fog_area": "67", "max_num": "3"}, {"id": "7000056", "name": "monster_point", "gid": "298", "x": "9988.53", "y": "4215.26", "width": "69", "height": "81", "fog_area": "67", "max_num": "3"}, {"id": "7000055", "name": "monster_point", "gid": "287", "x": "8572.95", "y": "2704", "width": "65", "height": "72", "fog_area": "68", "max_num": "4"}, {"id": "7000055", "name": "monster_point", "gid": "287", "x": "8940.83", "y": "1420.97", "width": "65", "height": "72", "fog_area": "68", "max_num": "4"}, {"id": "7000058", "name": "monster_point", "gid": "294", "x": "8088.53", "y": "1769.8", "width": "69", "height": "81", "fog_area": "68", "max_num": "4"}, {"id": "7000056", "name": "monster_point", "gid": "298", "x": "9011.56", "y": "2198.29", "width": "69", "height": "81", "fog_area": "68", "max_num": "2"}, {"id": "7000055", "name": "monster_point", "gid": "287", "x": "8335.98", "y": "1783.39", "width": "65", "height": "72", "fog_area": "68", "max_num": "2"}, {"id": "7000055", "name": "monster_point", "gid": "287", "x": "9857.2", "y": "1831.88", "width": "65", "height": "72", "fog_area": "69", "max_num": "4"}, {"id": "7000057", "name": "monster_point", "gid": "305", "x": "10671.1", "y": "1696.73", "width": "71", "height": "80", "fog_area": "69", "max_num": "4"}, {"id": "7000058", "name": "monster_point", "gid": "294", "x": "10425.5", "y": "2190.41", "width": "69", "height": "81", "fog_area": "69", "max_num": "4"}, {"id": "7000058", "name": "monster_point", "gid": "294", "x": "11685.5", "y": "2112.23", "width": "69", "height": "81", "fog_area": "69", "max_num": "4"}, {"id": "7000057", "name": "monster_point", "gid": "305", "x": "11877.8", "y": "2004.24", "width": "71", "height": "80", "fog_area": "69", "max_num": "4"}, {"id": "7000055", "name": "monster_point", "gid": "287", "x": "11170.5", "y": "2039.76", "width": "65", "height": "72", "fog_area": "69", "max_num": "2"}, {"id": "7000058", "name": "monster_point", "gid": "294", "x": "9821.26", "y": "1291.62", "width": "69", "height": "81", "fog_area": "69", "max_num": "4"}, {"id": "7000058", "name": "monster_point", "gid": "294", "x": "11247.9", "y": "3180.11", "width": "69", "height": "81", "fog_area": "70", "max_num": "4"}, {"id": "7000058", "name": "monster_point", "gid": "294", "x": "11180", "y": "4399.5", "width": "69", "height": "81", "fog_area": "70", "max_num": "4"}, {"id": "7000058", "name": "monster_point", "gid": "294", "x": "9909.14", "y": "3106.77", "width": "69", "height": "81", "fog_area": "70", "max_num": "4"}, {"id": "7000058", "name": "monster_point", "gid": "294", "x": "12080", "y": "4008.59", "width": "69", "height": "81", "fog_area": "70", "max_num": "4"}, {"id": "7000055", "name": "monster_point", "gid": "287", "x": "10580.8", "y": "3690.06", "width": "65", "height": "72", "fog_area": "70", "max_num": "2"}, {"id": "7000055", "name": "monster_point", "gid": "287", "x": "11730.5", "y": "3534.3", "width": "65", "height": "72", "fog_area": "70", "max_num": "2"}, {"id": "7000055", "name": "monster_point", "gid": "287", "x": "11872.3", "y": "4792.48", "width": "65", "height": "72", "fog_area": "70", "max_num": "2"}, {"id": "7000055", "name": "monster_point", "gid": "287", "x": "12088.7", "y": "2957.94", "width": "65", "height": "72", "fog_area": "70", "max_num": "2"}, {"id": "7000057", "name": "monster_point", "gid": "305", "x": "10328.7", "y": "3007.88", "width": "71", "height": "80", "fog_area": "70", "max_num": "4"}, {"id": "7000057", "name": "monster_point", "gid": "305", "x": "11150.6", "y": "3840.61", "width": "71", "height": "80", "fog_area": "70", "max_num": "4"}, {"id": "7000057", "name": "monster_point", "gid": "305", "x": "11818.4", "y": "3239.39", "width": "71", "height": "80", "fog_area": "70", "max_num": "4"}, {"id": "7000057", "name": "monster_point", "gid": "305", "x": "11685.1", "y": "4542.42", "width": "71", "height": "80", "fog_area": "70", "max_num": "2"}, {"id": "7000057", "name": "monster_point", "gid": "305", "x": "10471.2", "y": "3913.94", "width": "71", "height": "80", "fog_area": "70", "max_num": "2"}, {"id": "7000058", "name": "monster_point", "gid": "294", "x": "13131.6", "y": "5223.74", "width": "69", "height": "81", "fog_area": "71", "max_num": "4"}, {"id": "7000058", "name": "monster_point", "gid": "294", "x": "13143.7", "y": "3290.41", "width": "69", "height": "81", "fog_area": "71", "max_num": "4"}, {"id": "7000057", "name": "monster_point", "gid": "305", "x": "12763.9", "y": "4384.85", "width": "71", "height": "80", "fog_area": "71", "max_num": "2"}, {"id": "7000057", "name": "monster_point", "gid": "305", "x": "13581.5", "y": "4009.7", "width": "71", "height": "80", "fog_area": "71", "max_num": "2"}, {"id": "7000057", "name": "monster_point", "gid": "305", "x": "12835.4", "y": "2725.45", "width": "71", "height": "80", "fog_area": "71", "max_num": "4"}]}